EzAudioMeta/__init__.py
EzAudioMeta/main.py
EzAudioMeta/audio/__init__.py
EzAudioMeta/audio/base_audio.py
EzAudioMeta/utilities/__init__.py
EzAudioMeta/utilities/optional_string_matchers.py
EzAudioMeta-0.2.dist-info/LICENSE
EzAudioMeta-0.2.dist-info/METADATA
EzAudioMeta-0.2.dist-info/WHEEL
EzAudioMeta-0.2.dist-info/entry_points.txt
EzAudioMeta-0.2.dist-info/top_level.txt
EzAudioMeta-0.2.dist-info/RECORD
