Metadata-Version: 2.1
Name: EzAudioMeta
Version: 0.2
Summary: Easy CLI audio metadata manipulator
Home-page: https://github.com/XrossFox/EzAudioMeta
Author: David del Real
License: MIT
Keywords: Audio Metadata CLI
Platform: UNKNOWN
Classifier: Programming Language :: Python :: 3
Classifier: License :: OSI Approved :: MIT License
Classifier: Operating System :: OS Independent
Classifier: Development Status :: 4 - Beta
Classifier: Environment :: Console
Classifier: Intended Audience :: End Users/Desktop
Classifier: Natural Language :: English
Classifier: Topic :: Multimedia
License-File: LICENSE
Requires-Dist: click (>=7.1.2)
Requires-Dist: music-tag (>=0.4.2)
Requires-Dist: mutagen (>=1.45.1)
